{
  "info": {
    "_postman_id": "044262a4-1c05-4682-80be-6a5f09b332d9",
    "name": "JWT Auth Test",
    "schema": "https://schema.getpostman.com/json/collection/v2.1.0/collection.json",
    "_exporter_id": "38889549",
    "_collection_link": "https://jsk444.postman.co/workspace/cb334352-2d36-4f55-8ec8-88a6e4dc5326/collection/38889549-044262a4-1c05-4682-80be-6a5f09b332d9?action=share&source=collection_link&creator=38889549"
  },
  "item": [
    {
      "name": "User Register",
      "request": {
        "method": "POST",
        "header": [],
        "body": {
          "mode": "raw",
          "raw": "{\r\n    \"email\":\"djproject3@gmail.com\",\r\n    \"name\":\"djproject\",\r\n    \"password\":\"djproject@33\",\r\n    \"password2\":\"djproject@33\",\r\n    \"tc\":\"True\"\r\n}",
          "options": {
            "raw": {
              "language": "json"
            }
          }
        },
        "url": {
          "raw": "http://127.0.0.1:8000/api/register/",
          "protocol": "http",
          "host": ["127", "0", "0", "1"],
          "port": "8000",
          "path": ["api", "register", ""]
        }
      },
      "response": []
    },
    {
      "name": "User Login",
      "request": {
        "method": "POST",
        "header": [],
        "body": {
          "mode": "raw",
          "raw": "{\r\n    \"email\":\"djproject9@gmail.com\",\r\n   \r\n    \"password\":\"dj\"\r\n}",
          "options": {
            "raw": {
              "language": "json"
            }
          }
        },
        "url": {
          "raw": "http://127.0.0.1:8000/api/login/",
          "protocol": "http",
          "host": ["127", "0", "0", "1"],
          "port": "8000",
          "path": ["api", "login", ""]
        }
      },
      "response": []
    },
    {
      "name": "User Profile",
      "protocolProfileBehavior": {
        "disableBodyPruning": true
      },
      "request": {
        "method": "GET",
        "header": [
          {
            "key": "Authorization",
            "value": "Bearer eyJhbGciOiJIUzI1NiIsInR5cCI6IkpXVCJ9.eyJ0b2tlbl90eXBlIjoiYWNjZXNzIiwiZXhwIjoxNzQxNjIyMjA4LCJpYXQiOjE3NDE2MjEwMDgsImp0aSI6IjE3ZmZmNDcyNjViMTQ1ZmY4NjJhYWRjZTdkMjE1N2YwIiwidXNlcl9pZCI6OH0.HF5hvW_IgnqGE3MDwVMZwOwIN9h6PJuiXdb0Cx22eKM",
            "type": "text"
          }
        ],
        "body": {
          "mode": "raw",
          "raw": "",
          "options": {
            "raw": {
              "language": "json"
            }
          }
        },
        "url": {
          "raw": "http://127.0.0.1:8000/api/profile/",
          "protocol": "http",
          "host": ["127", "0", "0", "1"],
          "port": "8000",
          "path": ["api", "profile", ""]
        }
      },
      "response": []
    },
    {
      "name": "Change Password",
      "request": {
        "method": "POST",
        "header": [
          {
            "key": "Authorization",
            "value": "Bearer        eyJhbGciOiJIUzI1NiIsInR5cCI6IkpXVCJ9.eyJ0b2tlbl90eXBlIjoiYWNjZXNzIiwiZXhwIjoxNzQxNjIyMjA4LCJpYXQiOjE3NDE2MjEwMDgsImp0aSI6IjE3ZmZmNDcyNjViMTQ1ZmY4NjJhYWRjZTdkMjE1N2YwIiwidXNlcl9pZCI6OH0.HF5hvW_IgnqGE3MDwVMZwOwIN9h6PJuiXdb0Cx22eKM",
            "type": "text"
          }
        ],
        "body": {
          "mode": "raw",
          "raw": "{\r\n    \"password\":\"god\",\r\n    \"password2\":\"god\"\r\n}",
          "options": {
            "raw": {
              "language": "json"
            }
          }
        },
        "url": {
          "raw": "http://127.0.0.1:8000/api/changepassword/",
          "protocol": "http",
          "host": ["127", "0", "0", "1"],
          "port": "8000",
          "path": ["api", "changepassword", ""]
        }
      },
      "response": []
    },
    {
      "name": "Reset Password",
      "request": {
        "method": "POST",
        "header": [
          {
            "key": "Accept",
            "value": "application/json",
            "type": "text"
          }
        ],
        "body": {
          "mode": "raw",
          "raw": "{\r\n   \"password\":\"djproject\",\r\n   \"password2\":\"djproject\"\r\n}",
          "options": {
            "raw": {
              "language": "json"
            }
          }
        },
        "url": {
          "raw": "http://127.0.0.1:8000/api/reset-password/Mg/cmgw2z-301d625cd4a4926d8dcd5b490d61fc46/",
          "protocol": "http",
          "host": ["127", "0", "0", "1"],
          "port": "8000",
          "path": [
            "api",
            "reset-password",
            "Mg",
            "cmgw2z-301d625cd4a4926d8dcd5b490d61fc46",
            ""
          ]
        }
      },
      "response": []
    },
    {
      "name": "Send Reset Password through Email",
      "request": {
        "method": "POST",
        "header": [],
        "body": {
          "mode": "raw",
          "raw": "{\r\n    \"email\":\"djproject9@gmail.com\"\r\n}",
          "options": {
            "raw": {
              "language": "json"
            }
          }
        },
        "url": {
          "raw": "http://127.0.0.1:8000/api/send-reset-password-email/",
          "protocol": "http",
          "host": ["127", "0", "0", "1"],
          "port": "8000",
          "path": ["api", "send-reset-password-email", ""]
        }
      },
      "response": []
    }
  ]
}
